kiner/__init__.py
kiner/producer.py
kiner-0.6.4.dist-info/METADATA
kiner-0.6.4.dist-info/RECORD
kiner-0.6.4.dist-info/WHEEL
kiner-0.6.4.dist-info/top_level.txt
