Metadata-Version: 2.1
Name: kiner
Version: 0.6.4
Summary: Python AWS Kinesis Producer
Home-page: https://github.com/bufferapp/kiner
Author: David Gasquez
Author-email: davidgasquez@buffer.com
License: MIT
Keywords: kinesis,producer,aws
Platform: UNKNOWN
Requires-Dist: boto3
Requires-Dist: future
